bin/staramr
staramr/SubCommand.py
staramr/Utils.py
staramr/__init__.py
staramr/blast/AbstractBlastDatabase.py
staramr/blast/JobHandler.py
staramr/blast/__init__.py
staramr/blast/plasmidfinder/PlasmidfinderBlastDatabase.py
staramr/blast/plasmidfinder/__init__.py
staramr/blast/pointfinder/PointfinderBlastDatabase.py
staramr/blast/pointfinder/PointfinderDatabaseInfo.py
staramr/blast/pointfinder/__init__.py
staramr/blast/resfinder/ResfinderBlastDatabase.py
staramr/blast/resfinder/__init__.py
staramr/blast/results/AMRHitHSP.py
staramr/blast/results/BlastHitPartitions.py
staramr/blast/results/BlastResultsParser.py
staramr/blast/results/__init__.py
staramr/blast/results/plasmidfinder/BlastResultsParserPlasmidfinder.py
staramr/blast/results/plasmidfinder/BlastResultsParserPlasmidfinderResistance.py
staramr/blast/results/plasmidfinder/PlasmidfinderHitHSP.py
staramr/blast/results/plasmidfinder/__init__.py
staramr/blast/results/pointfinder/BlastResultsParserPointfinder.py
staramr/blast/results/pointfinder/BlastResultsParserPointfinderResistance.py
staramr/blast/results/pointfinder/MutationPosition.py
staramr/blast/results/pointfinder/PointfinderHitHSP.py
staramr/blast/results/pointfinder/__init__.py
staramr/blast/results/pointfinder/codon/CodonInsertionPosition.py
staramr/blast/results/pointfinder/codon/CodonMutationPosition.py
staramr/blast/results/pointfinder/codon/__init__.py
staramr/blast/results/pointfinder/nucleotide/NucleotideMutationPosition.py
staramr/blast/results/pointfinder/nucleotide/PointfinderHitHSPPromoter.py
staramr/blast/results/pointfinder/nucleotide/PointfinderHitHSPRNA.py
staramr/blast/results/pointfinder/nucleotide/__init__.py
staramr/blast/results/resfinder/BlastResultsParserResfinder.py
staramr/blast/results/resfinder/BlastResultsParserResfinderResistance.py
staramr/blast/results/resfinder/ResfinderHitHSP.py
staramr/blast/results/resfinder/__init__.py
staramr/databases/AMRDatabasesManager.py
staramr/databases/BlastDatabaseRepositories.py
staramr-0.11.0.dist-info/LICENSE
staramr-0.11.0.dist-info/METADATA
staramr-0.11.0.dist-info/NOTICE
staramr-0.11.0.dist-info/WHEEL
staramr-0.11.0.dist-info/top_level.txt
staramr-0.11.0.dist-info/RECORD
