Metadata-Version: 2.1
Name: staramr
Version: 0.11.0
Summary: Scans genome contigs against ResFinder, PlasmidFinder, and PointFinder databases
Home-page: https://github.com/phac-nml/staramr
Author: Aaron Petkau
Author-email: aaron.petkau@gmail.com
License: Apache v2.0
Classifier: Development Status :: 4 - Beta
Classifier: Environment :: Console
Classifier: License :: OSI Approved :: Apache Software License
Classifier: Intended Audience :: Science/Research
Classifier: Topic :: Scientific/Engineering
Classifier: Topic :: Scientific/Engineering :: Bio-Informatics
Classifier: Programming Language :: Python :: 3.5
Classifier: Programming Language :: Python :: 3.6
Classifier: Operating System :: POSIX :: Linux
License-File: LICENSE
License-File: NOTICE
Requires-Dist: biopython>=1.70
Requires-Dist: pandas>=0.23.0
Requires-Dist: GitPython>=2.1.3
Requires-Dist: xlsxwriter>=1.0.2
Requires-Dist: numpy>=1.12.1
Requires-Dist: green>=2.13.0
Requires-Dist: coloredlogs>=10.0
